cpca.py
cpca_drawers.py
chinese_province_city_area_mapper/__init__.py
chinese_province_city_area_mapper/domain.py
chinese_province_city_area_mapper/exceptions.py
chinese_province_city_area_mapper/infrastructure.py
chinese_province_city_area_mapper/mappers.py
chinese_province_city_area_mapper/transformer.py
cpca_fix-0.3.5.dist-info/LICENSE
cpca_fix-0.3.5.dist-info/METADATA
cpca_fix-0.3.5.dist-info/WHEEL
cpca_fix-0.3.5.dist-info/top_level.txt
cpca_fix-0.3.5.dist-info/RECORD
