Metadata-Version: 2.1
Name: cpca-fix
Version: 0.3.5
Summary: Chinese Province, City and Area Recognition Utilities
Home-page: https://github.com/LanjiaoGong/chinese_province_city_area_mapper
Author: DQinYuan
Author-email: sa517067@mail.ustc.edu.cn
License: MIT
Keywords: Simplified Chinese,Chinese geographic information,Chinese province city and area recognition and map
Platform: UNKNOWN
Classifier: Intended Audience :: Developers
Classifier: License :: OSI Approved :: MIT License
Classifier: Operating System :: OS Independent
Classifier: Natural Language :: Chinese (Simplified)
Classifier: Programming Language :: Python :: 3.6
Classifier: Topic :: Text Processing
Classifier: Topic :: Text Processing :: Indexing
Requires-Dist: pandas (>=0.20.0)
Requires-Dist: jieba (>=0.39)
